su.webdriver-0.2-py3.6-nspkg.pth
su/webdriver.py
su.webdriver-0.2.dist-info/DESCRIPTION.rst
su.webdriver-0.2.dist-info/METADATA
su.webdriver-0.2.dist-info/RECORD
su.webdriver-0.2.dist-info/WHEEL
su.webdriver-0.2.dist-info/metadata.json
su.webdriver-0.2.dist-info/namespace_packages.txt
su.webdriver-0.2.dist-info/top_level.txt
