Metadata-Version: 2.0
Name: su.webdriver
Version: 0.2
Summary: Webdriver with shortcuts.
Home-page: https://bitbucket.org/zhaolins/su.webdriver
Author: Zhaolin Su
Author-email: UNKNOWN
License: MIT
Platform: UNKNOWN
Requires-Dist: setuptools
Requires-Dist: pytz
Requires-Dist: su.password
